[
  {
    "map_id": 100,
    "size": 8,
    "percentage_obstacles": "0.09",
    "map": [
      [
        0,
        0,
        1,
        0,
        0,
        0,
        1,
        0
      ],
      [
        0,
        0,
        1,
        0,
        0,
        0,
        0,
        0
      ],
      [
        0,
        0,
        0,
        0,
        0,
        0,
        0,
        0
      ],
      [
        1,
        0,
        0,
        0,
        0,
        0,
        0,
        0
      ],
      [
        0,
        0,
        0,
        0,
        0,
        0,
        0,
        0
      ],
      [
        0,
        0,
        0,
        0,
        0,
        0,
        0,
        0
      ],
      [
        0,
        0,
        0,
        0,
        0,
        0,
        0,
        0
      ],
      [
        0,
        0,
        0,
        0,
        1,
        0,
        0,
        0
      ]
    ],
    "instances": [
      {
        "id": 1000000,
        "source_destination": [
          9,
          46
        ]
      },
      {
        "id": 1000001,
        "source_destination": [
          38,
          14
        ]
      },
      {
        "id": 1000002,
        "source_destination": [
          1,
          20
        ]
      },
      {
        "id": 1000003,
        "source_destination": [
          54,
          16
        ]
      },
      {
        "id": 1000004,
        "source_destination": [
          18,
          57
        ]
      },
      {
        "id": 1000005,
        "source_destination": [
          49,
          57
        ]
      },
      {
        "id": 1000006,
        "source_destination": [
          61,
          41
        ]
      },
      {
        "id": 1000007,
        "source_destination": [
          32,
          7
        ]
      },
      {
        "id": 1000008,
        "source_destination": [
          55,
          38
        ]
      },
      {
        "id": 1000009,
        "source_destination": [
          42,
          23
        ]
      }
    ]
  }
]