[
  {
    "map_id": 79,
    "size": 8,
    "percentage_obstacles": "0.37",
    "map": [
      [
        1,
        1,
        0,
        1,
        0,
        1,
        0,
        1
      ],
      [
        0,
        0,
        0,
        1,
        0,
        1,
        0,
        1
      ],
      [
        1,
        0,
        0,
        0,
        0,
        0,
        0,
        1
      ],
      [
        0,
        0,
        1,
        0,
        0,
        1,
        0,
        0
      ],
      [
        0,
        1,
        0,
        0,
        1,
        1,
        0,
        0
      ],
      [
        1,
        0,
        1,
        0,
        1,
        1,
        0,
        0
      ],
      [
        0,
        0,
        0,
        0,
        0,
        1,
        1,
        0
      ],
      [
        0,
        0,
        0,
        1,
        0,
        1,
        0,
        0
      ]
    ],
    "instances": [
      {
        "id": 790000,
        "source_destination": [
          63,
          21
        ]
      },
      {
        "id": 790001,
        "source_destination": [
          30,
          27
        ]
      },
      {
        "id": 790002,
        "source_destination": [
          9,
          31
        ]
      },
      {
        "id": 790003,
        "source_destination": [
          31,
          51
        ]
      },
      {
        "id": 790004,
        "source_destination": [
          56,
          32
        ]
      },
      {
        "id": 790005,
        "source_destination": [
          2,
          14
        ]
      },
      {
        "id": 790006,
        "source_destination": [
          34,
          41
        ]
      },
      {
        "id": 790007,
        "source_destination": [
          57,
          62
        ]
      },
      {
        "id": 790008,
        "source_destination": [
          4,
          20
        ]
      },
      {
        "id": 790009,
        "source_destination": [
          21,
          34
        ]
      }
    ]
  }
]